power_playlists/__init__.py
power_playlists/_version.py
power_playlists/main.py
power_playlists/nodes.py
power_playlists/spotify_client.py
power_playlists/utils.py
power_playlists-0.1.0.dist-info/METADATA
power_playlists-0.1.0.dist-info/WHEEL
power_playlists-0.1.0.dist-info/entry_points.txt
power_playlists-0.1.0.dist-info/licenses/LICENSE
power_playlists-0.1.0.dist-info/RECORD
