Metadata-Version: 2.4
Name: power-playlists
Version: 0.1.0
Summary: A Python CLI tool for creating dynamic Spotify playlists using YAML configuration files
Project-URL: Homepage, https://github.com/xkrogen/power-playlists/
Project-URL: Repository, https://github.com/xkrogen/power-playlists
Project-URL: Bug Tracker, https://github.com/xkrogen/power-playlists/issues
Project-URL: Documentation, https://xkrogen.github.io/power-playlists/
Author-email: Erik Krogen <erikkrogen@gmail.com>
License: MIT
License-File: LICENSE
Keywords: automation,cli,music,playlists,spotify,yaml
Classifier: Development Status :: 4 - Beta
Classifier: Intended Audience :: End Users/Desktop
Classifier: License :: OSI Approved :: MIT License
Classifier: Operating System :: POSIX
Classifier: Operating System :: Unix
Classifier: Programming Language :: Python
Classifier: Programming Language :: Python :: 3.9
Classifier: Programming Language :: Python :: 3.10
Classifier: Programming Language :: Python :: 3.11
Classifier: Programming Language :: Python :: 3.12
Classifier: Programming Language :: Python :: Implementation :: CPython
Classifier: Programming Language :: Python :: Implementation :: PyPy
Classifier: Topic :: Multimedia :: Sound/Audio
Classifier: Topic :: Utilities
Requires-Python: >=3.9
Requires-Dist: click<9,>=8.0
Requires-Dist: lockfile>=0.12
Requires-Dist: psutil<6,>=5.9
Requires-Dist: python-daemon<4,>=3.0
Requires-Dist: python-dateutil<3,>=2.8.1
Requires-Dist: pyyaml<7,>=6.0
Requires-Dist: setuptools>=65.0
Requires-Dist: spotipy<3,>=2.24.0
Provides-Extra: dev
Requires-Dist: pdoc>=15.0.0; extra == 'dev'
Requires-Dist: pytest~=7.4.4; extra == 'dev'
Provides-Extra: docs
Requires-Dist: pdoc>=15.0.0; extra == 'docs'
Provides-Extra: test
Requires-Dist: pytest~=7.4.4; extra == 'test'
